CHANGELOG
CONTRIBUTORS
LICENSE
MANIFEST.in
README.rst
da.py
requirements-devel.txt
requirements-py2.txt
requirements.txt
setup.py
devassistant/__init__.py
devassistant/__main__.py
devassistant/actions.py
devassistant/argument.py
devassistant/assistant_base.py
devassistant/bin.py
devassistant/cache.py
devassistant/command_helpers.py
devassistant/command_runners.py
devassistant/config_manager.py
devassistant/excepthook.py
devassistant/exceptions.py
devassistant/lang.py
devassistant/loaded_yaml.py
devassistant/logger.py
devassistant/package_managers.py
devassistant/path_runner.py
devassistant/remote_auth.py
devassistant/settings.py
devassistant/sigint_handler.py
devassistant/snippet.py
devassistant/utils.py
devassistant/yaml_assistant.py
devassistant/yaml_assistant_loader.py
devassistant/yaml_checker.py
devassistant/yaml_loader.py
devassistant/yaml_snippet_loader.py
devassistant.egg-info/PKG-INFO
devassistant.egg-info/SOURCES.txt
devassistant.egg-info/dependency_links.txt
devassistant.egg-info/entry_points.txt
devassistant.egg-info/pbr.json
devassistant.egg-info/requires.txt
devassistant.egg-info/top_level.txt
devassistant/cli/__init__.py
devassistant/cli/argparse_generator.py
devassistant/cli/cli_runner.py
devassistant/cli/devassistant_argparse.py
devassistant/dapi/__init__.py
devassistant/dapi/dapicli.py
devassistant/dapi/dapver.py
devassistant/dapi/licenses.py
devassistant/dapi/platforms.py
devassistant/gui/__init__.py
devassistant/gui/devel-assistant.glade
devassistant/gui/devel-yaml.glade
devassistant/gui/gui_helper.py
devassistant/gui/main_window.py
devassistant/gui/path_window.py
devassistant/gui/run_window.py
distribution/da.bash
distribution/devassistant.desktop
distribution/appdata/devassistant-main-window.png
distribution/appdata/devassistant-params-window.png
distribution/appdata/devassistant.appdata.xml
distribution/icons/hicolor/16x16/devassistant.png
distribution/icons/hicolor/22x22/devassistant.png
distribution/icons/hicolor/24x24/devassistant.png
distribution/icons/hicolor/256x256/devassistant.png
distribution/icons/hicolor/32x32/devassistant.png
distribution/icons/hicolor/48x48/devassistant.png
distribution/icons/hicolor/symbolic/devassistant-symbolic.svg
distribution/manpages/da-gui.txt
