Metadata-Version: 1.1
Name: devassistant
Version: 0.11.2
Summary: DevAssistant helps you kickstart your projects with ease.
Home-page: https://github.com/bkabrda/devassistant
Author: Bohuslav "Slavek" Kabrda
Author-email: bkabrda@redhat.com
License: GPLv2+
Keywords: develop,kickstart,easy,quick
Platform: UNKNOWN
Classifier: Development Status :: 4 - Beta
Classifier: Environment :: Console
Classifier: Intended Audience :: Developers
Classifier: License :: OSI Approved :: GNU General Public License v2 or later (GPLv2+)
Classifier: Operating System :: POSIX :: Linux
Classifier: Programming Language :: Python
Classifier: Topic :: Software Development
